{
    "leto": "2024",
    "odsek": "vopd",
    "seznam": [
        {
            "Datum": "20.1.2024",
            "Cilj": "Vrhovi nad Soriško planino",
            "Vodja": "Marija Kuhar",
            "Opis": "zimska, lahka"
        },
        {
            "Datum": "17.2.2024",
            "Cilj": "Viševnik, zimski športi",
            "Vodja": "Jernej Žnidaršič, Česnik Rajko",
            "Opis": "zimska, hoja, smučanje"
        },
        {
            "Datum": "2.3.2024",
            "Cilj": "Planinski dan žena in dan mučenikov",
            "Vodja": "Nika Čuk",
            "Opis": "lahka"
        },
        {
            "Datum": "16.3.2024",
            "Cilj": "Krk za prijatelje",
            "Vodja": "PS Bazovica, Valentina Posega",
            "Opis": "lahka"
        },
        {
            "Datum": "6.4.2024",
            "Cilj": "Rudolfovanje, Novo mesto",
            "Vodja": "Pohodniško društvo Novo mesto, Valentina Posega",
            "Opis": "različne ture, tudi kolesarske"
        },
        {
            "Datum": "14.4.2024",
            "Cilj": "Velika planina",
            "Vodja": "Hana Čuk",
            "Opis": "lahka"
        },
        {
            "Datum": "26.4. - 28.4.2024",
            "Cilj": "S pogledom na morje",
            "Vodja": "Valentina Posega, Marija Kuhar",
            "Opis": "različne ture, lahke, 2 ali 3 dni"
        },
        {
            "Datum": "26.5.2024",
            "Cilj": "Snežnik iz Leskove doline",
            "Vodja": "Rajko Česnik, Jernej Žnidaršič",
            "Opis": "lahka"
        },
        {
            "Datum": "7.6. - 9.6.2024",
            "Cilj": "26. srečanje planincev Balkana - Tetovo, Šar planina, PK Ljuboten",
            "Vodja": "PK Ljuboten (Tetovo Severna Makedonija), Valentina Posega",
            "Opis": "več tur, lahke, 3 dni srečanje, 6 dni skupaj"
        },
        {
            "Datum": "15.6.2024",
            "Cilj": "Dan planincev",
            "Vodja": "Neva Šemrov, Marija Kuhar",
            "Opis": "različne ture, tudi kolesarske"
        },
        {
            "Datum": "7.7.2024",
            "Cilj": "Po furmanskih poteh s planinci Balkana",
            "Vodja": "Valentina Posega, Marija Kuhar",
            "Opis": "lahka"
        },
        {
            "Datum": "13.7.2024",
            "Cilj": "Špik",
            "Vodja": "Jernej Žnidaršič, Rajko Česnik",
            "Opis": "zahtevna"
        },
        {
            "Datum": "21.7. - 28.7.2024",
            "Cilj": "Tabor PD Postojna",
            "Vodja": "VSI vodniki",
            "Opis": "različne skupine, različne ture, 7 dni"
        },
        {
            "Datum": "17.8. - 18.8.2024",
            "Cilj": "Čez planke s Furotom",
            "Vodja": "Aleksander Furlan, Rajko Česnik",
            "Opis": "več tur, lahke, zelo zahtevne, 2 dni"
        },
        {
            "Datum": "14.9.2024",
            "Cilj": "Rjavina",
            "Vodja": "Jernej in Tina Žnidaršič",
            "Opis": "za dijake in študente"
        },
        {
            "Datum": "15.9.2024",
            "Cilj": "Lisec",
            "Vodja": "Marija Kuhar",
            "Opis": "lahka"
        },
        {
            "Datum": "12.10.2024",
            "Cilj": "Visoki Mavrinc",
            "Vodja": "Nika Čuk",
            "Opis": "za otroke in odrasle, lahka"
        },
        {
            "Datum": "19.10.2024",
            "Cilj": "Ciprnik",
            "Vodja": "Tina Žnidaršič",
            "Opis": "lahka"
        },
        {
            "Datum": "17.11.2024",
            "Cilj": "Glinščica",
            "Vodja": "Erika Mahnič, Aleksander Furlan",
            "Opis": "za otroke in odrasle, lahka"
        },
        {
            "Datum": "26.12.2024",
            "Cilj": "Izlet presenečenja",
            "Vodja": "Tanja Žele",
            "Opis": "lahka, zimska"
        }
    ]
}